odoo10_addon_auth_user_case_insensitive-10.0.1.0.1-nspkg.pth
odoo/addons/auth_user_case_insensitive/README.rst
odoo/addons/auth_user_case_insensitive/__init__.py
odoo/addons/auth_user_case_insensitive/__manifest__.py
odoo/addons/auth_user_case_insensitive/hooks.py
odoo/addons/auth_user_case_insensitive/i18n/ar.po
odoo/addons/auth_user_case_insensitive/i18n/auth_user_case_insensitive.pot
odoo/addons/auth_user_case_insensitive/i18n/ca.po
odoo/addons/auth_user_case_insensitive/i18n/da.po
odoo/addons/auth_user_case_insensitive/i18n/de.po
odoo/addons/auth_user_case_insensitive/i18n/el_GR.po
odoo/addons/auth_user_case_insensitive/i18n/es.po
odoo/addons/auth_user_case_insensitive/i18n/es_ES.po
odoo/addons/auth_user_case_insensitive/i18n/fi.po
odoo/addons/auth_user_case_insensitive/i18n/fr.po
odoo/addons/auth_user_case_insensitive/i18n/fr_CH.po
odoo/addons/auth_user_case_insensitive/i18n/fr_FR.po
odoo/addons/auth_user_case_insensitive/i18n/hr.po
odoo/addons/auth_user_case_insensitive/i18n/hr_HR.po
odoo/addons/auth_user_case_insensitive/i18n/it.po
odoo/addons/auth_user_case_insensitive/i18n/nl.po
odoo/addons/auth_user_case_insensitive/i18n/nl_NL.po
odoo/addons/auth_user_case_insensitive/i18n/pt.po
odoo/addons/auth_user_case_insensitive/i18n/pt_BR.po
odoo/addons/auth_user_case_insensitive/i18n/ro.po
odoo/addons/auth_user_case_insensitive/i18n/sl.po
odoo/addons/auth_user_case_insensitive/i18n/tr.po
odoo/addons/auth_user_case_insensitive/i18n/tr_TR.po
odoo/addons/auth_user_case_insensitive/i18n/zh_CN.po
odoo/addons/auth_user_case_insensitive/models/__init__.py
odoo/addons/auth_user_case_insensitive/models/res_users.py
odoo/addons/auth_user_case_insensitive/static/description/icon.png
odoo/addons/auth_user_case_insensitive/tests/__init__.py
odoo/addons/auth_user_case_insensitive/tests/test_res_users.py
odoo10_addon_auth_user_case_insensitive-10.0.1.0.1.dist-info/METADATA
odoo10_addon_auth_user_case_insensitive-10.0.1.0.1.dist-info/WHEEL
odoo10_addon_auth_user_case_insensitive-10.0.1.0.1.dist-info/namespace_packages.txt
odoo10_addon_auth_user_case_insensitive-10.0.1.0.1.dist-info/top_level.txt
odoo10_addon_auth_user_case_insensitive-10.0.1.0.1.dist-info/RECORD
